pandas_maxminddb-0.2.1.dist-info/METADATA
pandas_maxminddb-0.2.1.dist-info/WHEEL
pandas_maxminddb-0.2.1.dist-info/license_files/LICENSE.md
pandas_maxminddb.libs/libgcc_s-2ba33186.so.1
pandas_maxminddb/pandas_maxminddb.pyi
pandas_maxminddb/py.typed
pandas_maxminddb/__init__.py
pandas_maxminddb/pandas_maxminddb.cpython-310-x86_64-linux-gnu.so
pandas_maxminddb-0.2.1.dist-info/RECORD
