Metadata-Version: 2.1
Name: pandas-maxminddb
Version: 0.2.1
Classifier: License :: OSI Approved :: MIT License
Classifier: Development Status :: 4 - Beta
Classifier: Intended Audience :: Developers
Classifier: Intended Audience :: Science/Research
Classifier: Topic :: Scientific/Engineering :: GIS
Classifier: Programming Language :: Python
Classifier: Programming Language :: Rust
Classifier: Operating System :: POSIX
Classifier: Operating System :: MacOS :: MacOS X
Classifier: Operating System :: Microsoft :: Windows
Classifier: Operating System :: POSIX :: Linux
Requires-Dist: pandas
Requires-Dist: numpy
License-File: LICENSE.md
Summary: Fast geolocation library for Pandas Dataframes, built on Numpy C-FFI
Author: Andrew Korzhuev <korzhuev@andrusha.me>
Author-email: Andrew Korzhuev <korzhuev@andrusha.me>
License: MIT
Requires-Python: >=3.8
